{"singlePage": [], "startSite": "", "filingNum": "", "onePageListNum": 15, "commentLabelColor": "#006b75", "yearColorList": ["#bc4c00", "#0969da", "#1f883d", "#A333D0"], "i18n": "CN", "themeMode": "manual", "dayTheme": "light", "nightTheme": "dark", "urlMode": "pinyin", "script": "", "style": "", "head": "", "indexScript": "", "indexStyle": "", "bottomText": "", "showPostSource": 1, "iconList": {}, "UTC": 8, "rssSplit": "sentence", "exlink": {}, "needComment": 1, "allHead": "", "title": "\u62fe\u84f1\u7684\u535a\u5ba2", "subTitle": "\u8bb0\u5f55\u5b66\u4e60\u751f\u6d3b", "avatarUrl": "https://avatars.githubusercontent.com/u/232326179?v=4&size=64", "GMEEK_VERSION": "last", "postListJson": {"P1": {"htmlDir": "docs/post/test.html", "labels": ["documentation"], "postTitle": "test", "postUrl": "post/test.html", "postSourceUrl": "https://github.com/invalid-request/ysh.github.io/issues/1", "commentNum": 0, "wordCount": 11, "description": "hello world\u3002", "top": 0, "createdAt": 1780854196, "style": "", "script": "", "head": "", "ogImage": "https://avatars.githubusercontent.com/u/232326179?v=4&size=64", "createdDate": "2026-06-08", "dateLabelColor": "#1f883d"}, "P3": {"htmlDir": "docs/post/dong-nan-da-xue-suan-fa-shang-ji-shi-yan-ti-jie.html", "labels": ["documentation"], "postTitle": "\u4e1c\u5357\u5927\u5b66\u7b97\u6cd5\u4e0a\u673a\u5b9e\u9a8c\u9898\u89e3", "postUrl": "post/dong-nan-da-xue-suan-fa-shang-ji-shi-yan-ti-jie.html", "postSourceUrl": "https://github.com/invalid-request/ysh.github.io/issues/3", "commentNum": 0, "wordCount": 27258, "description": "# 1007 \u6700\u5927\u4e58\u79ef\n\n## \u9898\u76ee\n\n> \u8bbe\u6709\u4e00\u4e2a\u957f\u5ea6\u4e3aN\u7684\u6570\u5b57\u4e32\uff0c\u8981\u6c42\u9009\u624b\u4f7f\u7528K\u4e2a\u4e58\u53f7\u5c06\u5b83\u5206\u6210`K+1`\u4e2a\u90e8\u5206\uff0c\u627e\u51fa\u4e00\u79cd\u5206\u6cd5\uff0c\u4f7f\u5f97\u8fd9`K+1`\u4e2a\u90e8\u5206\u7684\u4e58\u79ef\u80fd\u591f\u4e3a\u6700\u5927\u3002", "top": 0, "createdAt": 1780855030, "style": "", "script": "", "head": "", "ogImage": "https://avatars.githubusercontent.com/u/232326179?v=4&size=64", "createdDate": "2026-06-08", "dateLabelColor": "#1f883d"}}, "singeListJson": {}, "labelColorDict": {"bug": "#d73a4a", "documentation": "#0075ca", "duplicate": "#cfd3d7", "enhancement": "#a2eeef", "good first issue": "#7057ff", "help wanted": "#008672", "invalid": "#e4e669", "question": "#d876e3", "wontfix": "#ffffff"}, "displayTitle": "\u62fe\u84f1\u7684\u535a\u5ba2", "faviconUrl": "https://avatars.githubusercontent.com/u/232326179?v=4&size=64", "ogImage": "https://avatars.githubusercontent.com/u/232326179?v=4&size=64", "primerCSS": "<link href='https://mirrors.sustech.edu.cn/cdnjs/ajax/libs/Primer/21.0.7/primer.css' rel='stylesheet' />", "homeUrl": "https://invalid-request.github.io/ysh.github.io", "prevUrl": "disabled", "nextUrl": "disabled"}